{
  "model": {
    "type": "minecraft:select",
    "property": "minecraft:component",
    "component": "minecraft:custom_name",
    "cases": [
      {
        "when": {
          "text": "曲がった矢",
          "color": "white",
          "bold": true,
          "italic": false
        },
        "model": {
          "type": "minecraft:model",
          "model": "dekitate_event:item/no166/curved_arrow"
        }
      },
      {
        "when": {
          "text": "次へ",
          "color": "white",
          "italic": false
        },
        "model": {
          "type": "minecraft:model",
          "model": "dekitate_event:item/dpass/next"
        }
      },
      {
        "when": {
          "text": "戻る",
          "color": "white",
          "bold": true,
          "italic": false
        },
        "model": {
          "type": "minecraft:model",
          "model": "dekitate_event:item/dpass/back"
        }
      }
    ],
    "fallback": {
      "type": "minecraft:model",
      "model": "minecraft:item/arrow"
    }
  }
}