{
  "model": {
    "type": "minecraft:select",
    "property": "minecraft:component",
    "component": "minecraft:custom_name",
    "cases": [
      {
        "when": {
          "text": "翡翠の勾玉",
          "color": "green",
          "italic": false,
          "bold": true
        },
        "model": {
          "type": "minecraft:model",
          "model": "dekitate_event:item/yomi/hisui"
        }
      }
    ],
    "fallback": {
      "type": "minecraft:model",
      "model": "minecraft:item/emerald"
    }
  }
}