{
  "model": {
    "type": "minecraft:select",
    "property": "minecraft:component",
    "component": "minecraft:custom_name",
    "cases": [
      {
        "when": {
          "text": "時の剣",
          "color": "gold",
          "bold": true
        },
        "model": {
          "type": "minecraft:model",
          "model": "dekitate_event:item/time/toki_ken"
        }
      },
      {
        "when": {
          "text": "ランク",
          "color": "white",
          "bold": true,
          "italic": false
        },
        "model": {
          "type": "minecraft:model",
          "model": "dekitate_event:item/dpass/d_rank"
        }
      },
      {
        "when": {
          "text": "Dランク",
          "color": "white",
          "bold": true,
          "italic": false
        },
        "model": {
          "type": "minecraft:model",
          "model": "dekitate_event:item/dpass/d_rank"
        }
      }
    ],
    "fallback": {
      "type": "minecraft:model",
      "model": "minecraft:item/wooden_sword"
    }
  }
}